bitmasher_game/TextBasedGame.py
bitmasher_game/__init__.py
bitmasher_game-5.74351224532.dist-info/LICENSE
bitmasher_game-5.74351224532.dist-info/METADATA
bitmasher_game-5.74351224532.dist-info/WHEEL
bitmasher_game-5.74351224532.dist-info/entry_points.txt
bitmasher_game-5.74351224532.dist-info/top_level.txt
bitmasher_game-5.74351224532.dist-info/RECORD
