Metadata-Version: 2.1
Name: bitmasher_game
Version: 5.74351224532
Summary: BitMasher, a text adventure game where you act as an antivirus attempting to rid a computer of a RANSOMWARE attack.
Home-page: https://github.com/ona-li-toki-e-jan-Epiphany-tawa-mi/BitMasher
Download-URL: https://github.com/ona-li-toki-e-jan-Epiphany-tawa-mi/BitMasher/releases
Author: ona li toki e jan Epiphany tawa mi
License: MIT
Keywords: BitMasher,text-adventure-based game,cli,game,fast-paced,text-game
Platform: Windows
Platform: POSIX
Classifier: Environment :: Console
Classifier: Intended Audience :: End Users/Desktop
Classifier: Natural Language :: English
Classifier: Operating System :: Microsoft :: Windows
Classifier: Operating System :: POSIX
Classifier: Programming Language :: Python :: 3
Classifier: Topic :: Games/Entertainment :: Arcade
License-File: LICENSE
